{
  "manifestVersion": "3.2",
  "admin": {
    "address": "0xbCd2D53e9A2F4E64752f507BeB9E833B647B8889",
    "txHash": "0xfca03cb0bd37a05a8820690dd7e8df7407157432a21b8966ba0f82042e5c42fe"
  },
  "proxies": [
    {
      "address": "0x597fbC82F0c6B026537CFAb42623Bb702F9CDdBc",
      "txHash": "0x6b10e5576d0a44709647dddfed6a6a3258029e596a9dd7a908faeeb7f428d83f",
      "kind": "transparent"
    },
    {
      "address": "0xD6b8faF86Aa90cbFf34CF8161f35eFC8dd59056c",
      "txHash": "0xd7d8c79f92b89cf5602cf91a3458dccda5e9697021142a7ba0d5058e4f4677dd",
      "kind": "transparent"
    },
    {
      "address": "0x92ba53Fb2801cC1918916d62a6243eC47e278AFD",
      "txHash": "0xf379cbe6787593b04ee013540af2909202ae8a563aa3de02972352cd0c3f6396",
      "kind": "transparent"
    },
    {
      "address": "0x8388556C586F08DDdd9e4b113b4A4c9360746C48",
      "txHash": "0xd81ce9bc812ffade47ad3068dc0b98d96c7ff7aac1e4374ae8fe954a3bfdeecb",
      "kind": "transparent"
    },
    {
      "address": "0x8891E81916ECdE2E543bd346692792c9e2f42748",
      "txHash": "0x85a5b8fdd34ce63c42fcb425e6616daf3e62358c7cc158e02e4c2e2babd0f95b",
      "kind": "transparent"
    },
    {
      "address": "0xD0665559d51c88098540EcE8D068B4C3B339c259",
      "txHash": "0x87eeaa7ac637bf2dfce49be4983083c967a153f625b9777055bcef50e61574fb",
      "kind": "transparent"
    },
    {
      "address": "0x49d1f669DC48a1dc0D322f60ad1b8D6637A502A3",
      "txHash": "0xd143b2c9380d2c029740fad1bb485f1958efc2be9699205299b582aa93e584c0",
      "kind": "transparent"
    },
    {
      "address": "0xAc8408f23f406e25efD0F62dA51c8857f6C0f329",
      "txHash": "0x7f481e1eb304ae4e55ca9138623fb93234c78f1600cd448b0a76507d64750c53",
      "kind": "transparent"
    }
  ],
  "impls": {
    "ed2d419bc3887b329c6ad7391b823c1327b1a53b95af9a4b6b2c6236eafe0d45": {
      "address": "0xF18fd80399891E889081055a3DF4672D55984D5F",
      "txHash": "0x71ef391f67d3971d7698f353283d1e92b92dc93a42412b067513d95dd5fa503f",
      "layout": {
        "solcVersion": "0.8.13",
        "storage": [
          {
            "label": "_initialized",
            "offset": 0,
            "slot": "0",
            "type": "t_uint8",
            "contract": "Initializable",
            "src": "@openzeppelin/contracts-upgradeable/proxy/utils/Initializable.sol:62",
            "retypedFrom": "bool"
          },
          {
            "label": "_initializing",
            "offset": 1,
            "slot": "0",
            "type": "t_bool",
            "contract": "Initializable",
            "src": "@openzeppelin/contracts-upgradeable/proxy/utils/Initializable.sol:67"
          },
          {
            "label": "__gap",
            "offset": 0,
            "slot": "1",
            "type": "t_array(t_uint256)50_storage",
            "contract": "ContextUpgradeable",
            "src": "@openzeppelin/contracts-upgradeable/utils/ContextUpgradeable.sol:36"
          },
          {
            "label": "_owner",
            "offset": 0,
            "slot": "51",
            "type": "t_address",
            "contract": "OwnableUpgradeable",
            "src": "@openzeppelin/contracts-upgradeable/access/OwnableUpgradeable.sol:22"
          },
          {
            "label": "__gap",
            "offset": 0,
            "slot": "52",
            "type": "t_array(t_uint256)49_storage",
            "contract": "OwnableUpgradeable",
            "src": "@openzeppelin/contracts-upgradeable/access/OwnableUpgradeable.sol:94"
          },
          {
            "label": "last_bribe",
            "offset": 0,
            "slot": "101",
            "type": "t_address",
            "contract": "BribeFactoryV3",
            "src": "contracts/factories/BribeFactoryV3.sol:19"
          },
          {
            "label": "_bribes",
            "offset": 0,
            "slot": "102",
            "type": "t_array(t_address)dyn_storage",
            "contract": "BribeFactoryV3",
            "src": "contracts/factories/BribeFactoryV3.sol:20"
          },
          {
            "label": "voter",
            "offset": 0,
            "slot": "103",
            "type": "t_address",
            "contract": "BribeFactoryV3",
            "src": "contracts/factories/BribeFactoryV3.sol:21"
          },
          {
            "label": "defaultRewardToken",
            "offset": 0,
            "slot": "104",
            "type": "t_array(t_address)dyn_storage",
            "contract": "BribeFactoryV3",
            "src": "contracts/factories/BribeFactoryV3.sol:23"
          },
          {
            "label": "permissionsRegistry",
            "offset": 0,
            "slot": "105",
            "type": "t_contract(IPermissionsRegistry)50023",
            "contract": "BribeFactoryV3",
            "src": "contracts/factories/BribeFactoryV3.sol:25"
          }
        ],
        "types": {
          "t_address": {
            "label": "address",
            "numberOfBytes": "20"
          },
          "t_array(t_address)dyn_storage": {
            "label": "address[]",
            "numberOfBytes": "32"
          },
          "t_array(t_uint256)49_storage": {
            "label": "uint256[49]",
            "numberOfBytes": "1568"
          },
          "t_array(t_uint256)50_storage": {
            "label": "uint256[50]",
            "numberOfBytes": "1600"
          },
          "t_bool": {
            "label": "bool",
            "numberOfBytes": "1"
          },
          "t_contract(IPermissionsRegistry)50023": {
            "label": "contract IPermissionsRegistry",
            "numberOfBytes": "20"
          },
          "t_uint256": {
            "label": "uint256",
            "numberOfBytes": "32"
          },
          "t_uint8": {
            "label": "uint8",
            "numberOfBytes": "1"
          }
        }
      }
    },
    "d3842624a92802b2e9d98d4be485ce8da3aa52e19e15cc40f411695309ed24dd": {
      "address": "0xd3915391558D4e356BE0d54F612113F75A02f43C",
      "txHash": "0x50baa887effb5ce5f3377167fb5ec34b01761e4ec9cf2f6ef0f8d6b77a9a4bfe",
      "layout": {
        "solcVersion": "0.8.13",
        "storage": [
          {
            "label": "_initialized",
            "offset": 0,
            "slot": "0",
            "type": "t_uint8",
            "contract": "Initializable",
            "src": "@openzeppelin/contracts-upgradeable/proxy/utils/Initializable.sol:62",
            "retypedFrom": "bool"
          },
          {
            "label": "_initializing",
            "offset": 1,
            "slot": "0",
            "type": "t_bool",
            "contract": "Initializable",
            "src": "@openzeppelin/contracts-upgradeable/proxy/utils/Initializable.sol:67"
          },
          {
            "label": "__gap",
            "offset": 0,
            "slot": "1",
            "type": "t_array(t_uint256)50_storage",
            "contract": "ContextUpgradeable",
            "src": "@openzeppelin/contracts-upgradeable/utils/ContextUpgradeable.sol:36"
          },
          {
            "label": "_owner",
            "offset": 0,
            "slot": "51",
            "type": "t_address",
            "contract": "OwnableUpgradeable",
            "src": "@openzeppelin/contracts-upgradeable/access/OwnableUpgradeable.sol:22"
          },
          {
            "label": "__gap",
            "offset": 0,
            "slot": "52",
            "type": "t_array(t_uint256)49_storage",
            "contract": "OwnableUpgradeable",
            "src": "@openzeppelin/contracts-upgradeable/access/OwnableUpgradeable.sol:94"
          },
          {
            "label": "last_gauge",
            "offset": 0,
            "slot": "101",
            "type": "t_address",
            "contract": "GaugeFactoryV2",
            "src": "contracts/factories/GaugeFactoryV2.sol:23"
          },
          {
            "label": "permissionsRegistry",
            "offset": 0,
            "slot": "102",
            "type": "t_address",
            "contract": "GaugeFactoryV2",
            "src": "contracts/factories/GaugeFactoryV2.sol:24"
          },
          {
            "label": "__gauges",
            "offset": 0,
            "slot": "103",
            "type": "t_array(t_address)dyn_storage",
            "contract": "GaugeFactoryV2",
            "src": "contracts/factories/GaugeFactoryV2.sol:26"
          }
        ],
        "types": {
          "t_address": {
            "label": "address",
            "numberOfBytes": "20"
          },
          "t_array(t_address)dyn_storage": {
            "label": "address[]",
            "numberOfBytes": "32"
          },
          "t_array(t_uint256)49_storage": {
            "label": "uint256[49]",
            "numberOfBytes": "1568"
          },
          "t_array(t_uint256)50_storage": {
            "label": "uint256[50]",
            "numberOfBytes": "1600"
          },
          "t_bool": {
            "label": "bool",
            "numberOfBytes": "1"
          },
          "t_uint256": {
            "label": "uint256",
            "numberOfBytes": "32"
          },
          "t_uint8": {
            "label": "uint8",
            "numberOfBytes": "1"
          }
        }
      }
    },
    "4010ae1adff66da9104b5dc18c5f74bd3d11a9c13725d3cf894f030cb9779692": {
      "address": "0xD9446D75391446d7e90FEE970d551079ad0781b3",
      "txHash": "0x7e7a759718c103c4ef7358adc1f08739129a365ca66b4cda35b48fd297907272",
      "layout": {
        "solcVersion": "0.8.13",
        "storage": [
          {
            "label": "_initialized",
            "offset": 0,
            "slot": "0",
            "type": "t_uint8",
            "contract": "Initializable",
            "src": "@openzeppelin/contracts-upgradeable/proxy/utils/Initializable.sol:62",
            "retypedFrom": "bool"
          },
          {
            "label": "_initializing",
            "offset": 1,
            "slot": "0",
            "type": "t_bool",
            "contract": "Initializable",
            "src": "@openzeppelin/contracts-upgradeable/proxy/utils/Initializable.sol:67"
          },
          {
            "label": "__gap",
            "offset": 0,
            "slot": "1",
            "type": "t_array(t_uint256)50_storage",
            "contract": "ContextUpgradeable",
            "src": "@openzeppelin/contracts-upgradeable/utils/ContextUpgradeable.sol:36"
          },
          {
            "label": "_owner",
            "offset": 0,
            "slot": "51",
            "type": "t_address",
            "contract": "OwnableUpgradeable",
            "src": "@openzeppelin/contracts-upgradeable/access/OwnableUpgradeable.sol:22"
          },
          {
            "label": "__gap",
            "offset": 0,
            "slot": "52",
            "type": "t_array(t_uint256)49_storage",
            "contract": "OwnableUpgradeable",
            "src": "@openzeppelin/contracts-upgradeable/access/OwnableUpgradeable.sol:94"
          },
          {
            "label": "last_gauge",
            "offset": 0,
            "slot": "101",
            "type": "t_address",
            "contract": "GaugeFactoryV2_CL",
            "src": "contracts/factories/GaugeFactoryV2_CL.sol:24"
          },
          {
            "label": "last_feeVault",
            "offset": 0,
            "slot": "102",
            "type": "t_address",
            "contract": "GaugeFactoryV2_CL",
            "src": "contracts/factories/GaugeFactoryV2_CL.sol:25"
          },
          {
            "label": "permissionsRegistry",
            "offset": 0,
            "slot": "103",
            "type": "t_address",
            "contract": "GaugeFactoryV2_CL",
            "src": "contracts/factories/GaugeFactoryV2_CL.sol:26"
          },
          {
            "label": "gammaFeeRecipient",
            "offset": 0,
            "slot": "104",
            "type": "t_address",
            "contract": "GaugeFactoryV2_CL",
            "src": "contracts/factories/GaugeFactoryV2_CL.sol:27"
          },
          {
            "label": "__gauges",
            "offset": 0,
            "slot": "105",
            "type": "t_array(t_address)dyn_storage",
            "contract": "GaugeFactoryV2_CL",
            "src": "contracts/factories/GaugeFactoryV2_CL.sol:29"
          }
        ],
        "types": {
          "t_address": {
            "label": "address",
            "numberOfBytes": "20"
          },
          "t_array(t_address)dyn_storage": {
            "label": "address[]",
            "numberOfBytes": "32"
          },
          "t_array(t_uint256)49_storage": {
            "label": "uint256[49]",
            "numberOfBytes": "1568"
          },
          "t_array(t_uint256)50_storage": {
            "label": "uint256[50]",
            "numberOfBytes": "1600"
          },
          "t_bool": {
            "label": "bool",
            "numberOfBytes": "1"
          },
          "t_uint256": {
            "label": "uint256",
            "numberOfBytes": "32"
          },
          "t_uint8": {
            "label": "uint8",
            "numberOfBytes": "1"
          }
        }
      }
    },
    "a5c64ec08c2a4619c6b13289297a1dbfc6d2390ea6334dcd11ac037100bf2fbf": {
      "address": "0x15c05D06af62c3239b31ad672525b79f44214C44",
      "txHash": "0xae7585e416ef1df6732fc4a9fb86cf35bcf06c7a906566cfb2b678182e49a2fc",
      "layout": {
        "solcVersion": "0.8.13",
        "storage": [
          {
            "label": "_initialized",
            "offset": 0,
            "slot": "0",
            "type": "t_uint8",
            "contract": "Initializable",
            "src": "@openzeppelin/contracts-upgradeable/proxy/utils/Initializable.sol:62",
            "retypedFrom": "bool"
          },
          {
            "label": "_initializing",
            "offset": 1,
            "slot": "0",
            "type": "t_bool",
            "contract": "Initializable",
            "src": "@openzeppelin/contracts-upgradeable/proxy/utils/Initializable.sol:67"
          },
          {
            "label": "__gap",
            "offset": 0,
            "slot": "1",
            "type": "t_array(t_uint256)50_storage",
            "contract": "ContextUpgradeable",
            "src": "@openzeppelin/contracts-upgradeable/utils/ContextUpgradeable.sol:36"
          },
          {
            "label": "_owner",
            "offset": 0,
            "slot": "51",
            "type": "t_address",
            "contract": "OwnableUpgradeable",
            "src": "@openzeppelin/contracts-upgradeable/access/OwnableUpgradeable.sol:22"
          },
          {
            "label": "__gap",
            "offset": 0,
            "slot": "52",
            "type": "t_array(t_uint256)49_storage",
            "contract": "OwnableUpgradeable",
            "src": "@openzeppelin/contracts-upgradeable/access/OwnableUpgradeable.sol:94"
          },
          {
            "label": "_status",
            "offset": 0,
            "slot": "101",
            "type": "t_uint256",
            "contract": "ReentrancyGuardUpgradeable",
            "src": "@openzeppelin/contracts-upgradeable/security/ReentrancyGuardUpgradeable.sol:38"
          },
          {
            "label": "__gap",
            "offset": 0,
            "slot": "102",
            "type": "t_array(t_uint256)49_storage",
            "contract": "ReentrancyGuardUpgradeable",
            "src": "@openzeppelin/contracts-upgradeable/security/ReentrancyGuardUpgradeable.sol:80"
          },
          {
            "label": "initflag",
            "offset": 0,
            "slot": "151",
            "type": "t_bool",
            "contract": "VoterV3",
            "src": "contracts/VoterV3.sol:25"
          },
          {
            "label": "_ve",
            "offset": 1,
            "slot": "151",
            "type": "t_address",
            "contract": "VoterV3",
            "src": "contracts/VoterV3.sol:27"
          },
          {
            "label": "_factories",
            "offset": 0,
            "slot": "152",
            "type": "t_array(t_address)dyn_storage",
            "contract": "VoterV3",
            "src": "contracts/VoterV3.sol:28"
          },
          {
            "label": "base",
            "offset": 0,
            "slot": "153",
            "type": "t_address",
            "contract": "VoterV3",
            "src": "contracts/VoterV3.sol:29"
          },
          {
            "label": "_gaugeFactories",
            "offset": 0,
            "slot": "154",
            "type": "t_array(t_address)dyn_storage",
            "contract": "VoterV3",
            "src": "contracts/VoterV3.sol:30"
          },
          {
            "label": "bribefactory",
            "offset": 0,
            "slot": "155",
            "type": "t_address",
            "contract": "VoterV3",
            "src": "contracts/VoterV3.sol:31"
          },
          {
            "label": "minter",
            "offset": 0,
            "slot": "156",
            "type": "t_address",
            "contract": "VoterV3",
            "src": "contracts/VoterV3.sol:32"
          },
          {
            "label": "permissionRegistry",
            "offset": 0,
            "slot": "157",
            "type": "t_address",
            "contract": "VoterV3",
            "src": "contracts/VoterV3.sol:33"
          },
          {
            "label": "pools",
            "offset": 0,
            "slot": "158",
            "type": "t_array(t_address)dyn_storage",
            "contract": "VoterV3",
            "src": "contracts/VoterV3.sol:34"
          },
          {
            "label": "index",
            "offset": 0,
            "slot": "159",
            "type": "t_uint256",
            "contract": "VoterV3",
            "src": "contracts/VoterV3.sol:36"
          },
          {
            "label": "VOTE_DELAY",
            "offset": 0,
            "slot": "160",
            "type": "t_uint256",
            "contract": "VoterV3",
            "src": "contracts/VoterV3.sol:38"
          },
          {
            "label": "supplyIndex",
            "offset": 0,
            "slot": "161",
            "type": "t_mapping(t_address,t_uint256)",
            "contract": "VoterV3",
            "src": "contracts/VoterV3.sol:41"
          },
          {
            "label": "claimable",
            "offset": 0,
            "slot": "162",
            "type": "t_mapping(t_address,t_uint256)",
            "contract": "VoterV3",
            "src": "contracts/VoterV3.sol:42"
          },
          {
            "label": "gauges",
            "offset": 0,
            "slot": "163",
            "type": "t_mapping(t_address,t_address)",
            "contract": "VoterV3",
            "src": "contracts/VoterV3.sol:43"
          },
          {
            "label": "gaugesDistributionTimestmap",
            "offset": 0,
            "slot": "164",
            "type": "t_mapping(t_address,t_uint256)",
            "contract": "VoterV3",
            "src": "contracts/VoterV3.sol:44"
          },
          {
            "label": "poolForGauge",
            "offset": 0,
            "slot": "165",
            "type": "t_mapping(t_address,t_address)",
            "contract": "VoterV3",
            "src": "contracts/VoterV3.sol:45"
          },
          {
            "label": "internal_bribes",
            "offset": 0,
            "slot": "166",
            "type": "t_mapping(t_address,t_address)",
            "contract": "VoterV3",
            "src": "contracts/VoterV3.sol:46"
          },
          {
            "label": "external_bribes",
            "offset": 0,
            "slot": "167",
            "type": "t_mapping(t_address,t_address)",
            "contract": "VoterV3",
            "src": "contracts/VoterV3.sol:47"
          },
          {
            "label": "votes",
            "offset": 0,
            "slot": "168",
            "type": "t_mapping(t_uint256,t_mapping(t_address,t_uint256))",
            "contract": "VoterV3",
            "src": "contracts/VoterV3.sol:48"
          },
          {
            "label": "poolVote",
            "offset": 0,
            "slot": "169",
            "type": "t_mapping(t_uint256,t_array(t_address)dyn_storage)",
            "contract": "VoterV3",
            "src": "contracts/VoterV3.sol:49"
          },
          {
            "label": "weightsPerEpoch",
            "offset": 0,
            "slot": "170",
            "type": "t_mapping(t_uint256,t_mapping(t_address,t_uint256))",
            "contract": "VoterV3",
            "src": "contracts/VoterV3.sol:50"
          },
          {
            "label": "totalWeightsPerEpoch",
            "offset": 0,
            "slot": "171",
            "type": "t_mapping(t_uint256,t_uint256)",
            "contract": "VoterV3",
            "src": "contracts/VoterV3.sol:51"
          },
          {
            "label": "lastVoted",
            "offset": 0,
            "slot": "172",
            "type": "t_mapping(t_uint256,t_uint256)",
            "contract": "VoterV3",
            "src": "contracts/VoterV3.sol:52"
          },
          {
            "label": "isGauge",
            "offset": 0,
            "slot": "173",
            "type": "t_mapping(t_address,t_bool)",
            "contract": "VoterV3",
            "src": "contracts/VoterV3.sol:53"
          },
          {
            "label": "isWhitelisted",
            "offset": 0,
            "slot": "174",
            "type": "t_mapping(t_address,t_bool)",
            "contract": "VoterV3",
            "src": "contracts/VoterV3.sol:54"
          },
          {
            "label": "isAlive",
            "offset": 0,
            "slot": "175",
            "type": "t_mapping(t_address,t_bool)",
            "contract": "VoterV3",
            "src": "contracts/VoterV3.sol:55"
          },
          {
            "label": "isFactory",
            "offset": 0,
            "slot": "176",
            "type": "t_mapping(t_address,t_bool)",
            "contract": "VoterV3",
            "src": "contracts/VoterV3.sol:56"
          },
          {
            "label": "isGaugeFactory",
            "offset": 0,
            "slot": "177",
            "type": "t_mapping(t_address,t_bool)",
            "contract": "VoterV3",
            "src": "contracts/VoterV3.sol:57"
          }
        ],
        "types": {
          "t_address": {
            "label": "address",
            "numberOfBytes": "20"
          },
          "t_array(t_address)dyn_storage": {
            "label": "address[]",
            "numberOfBytes": "32"
          },
          "t_array(t_uint256)49_storage": {
            "label": "uint256[49]",
            "numberOfBytes": "1568"
          },
          "t_array(t_uint256)50_storage": {
            "label": "uint256[50]",
            "numberOfBytes": "1600"
          },
          "t_bool": {
            "label": "bool",
            "numberOfBytes": "1"
          },
          "t_mapping(t_address,t_address)": {
            "label": "mapping(address => address)",
            "numberOfBytes": "32"
          },
          "t_mapping(t_address,t_bool)": {
            "label": "mapping(address => bool)",
            "numberOfBytes": "32"
          },
          "t_mapping(t_address,t_uint256)": {
            "label": "mapping(address => uint256)",
            "numberOfBytes": "32"
          },
          "t_mapping(t_uint256,t_array(t_address)dyn_storage)": {
            "label": "mapping(uint256 => address[])",
            "numberOfBytes": "32"
          },
          "t_mapping(t_uint256,t_mapping(t_address,t_uint256))": {
            "label": "mapping(uint256 => mapping(address => uint256))",
            "numberOfBytes": "32"
          },
          "t_mapping(t_uint256,t_uint256)": {
            "label": "mapping(uint256 => uint256)",
            "numberOfBytes": "32"
          },
          "t_uint256": {
            "label": "uint256",
            "numberOfBytes": "32"
          },
          "t_uint8": {
            "label": "uint8",
            "numberOfBytes": "1"
          }
        }
      }
    },
    "a48f4ec5bdb38a39a8c51f52b291f979ba58ab1f191235116805c5d11f327ca1": {
      "address": "0x9f5a57603f765a45507772cDDeEAccaae5Cb1563",
      "txHash": "0xed214c6eac181807578816938b36119507f3b2b82174d7b74f1f9b3e23a13e0e",
      "layout": {
        "solcVersion": "0.8.13",
        "storage": [
          {
            "label": "_initialized",
            "offset": 0,
            "slot": "0",
            "type": "t_uint8",
            "contract": "Initializable",
            "src": "@openzeppelin/contracts-upgradeable/proxy/utils/Initializable.sol:62",
            "retypedFrom": "bool"
          },
          {
            "label": "_initializing",
            "offset": 1,
            "slot": "0",
            "type": "t_bool",
            "contract": "Initializable",
            "src": "@openzeppelin/contracts-upgradeable/proxy/utils/Initializable.sol:67"
          },
          {
            "label": "pairFactory",
            "offset": 2,
            "slot": "0",
            "type": "t_contract(IPairFactory)49269",
            "contract": "PairAPI",
            "src": "contracts/APIHelper/PairAPI.sol:85"
          },
          {
            "label": "voter",
            "offset": 0,
            "slot": "1",
            "type": "t_contract(IVoter)49885",
            "contract": "PairAPI",
            "src": "contracts/APIHelper/PairAPI.sol:86"
          },
          {
            "label": "underlyingToken",
            "offset": 0,
            "slot": "2",
            "type": "t_address",
            "contract": "PairAPI",
            "src": "contracts/APIHelper/PairAPI.sol:88"
          },
          {
            "label": "owner",
            "offset": 0,
            "slot": "3",
            "type": "t_address",
            "contract": "PairAPI",
            "src": "contracts/APIHelper/PairAPI.sol:90"
          }
        ],
        "types": {
          "t_address": {
            "label": "address",
            "numberOfBytes": "20"
          },
          "t_bool": {
            "label": "bool",
            "numberOfBytes": "1"
          },
          "t_contract(IPairFactory)49269": {
            "label": "contract IPairFactory",
            "numberOfBytes": "20"
          },
          "t_contract(IVoter)49885": {
            "label": "contract IVoter",
            "numberOfBytes": "20"
          },
          "t_uint8": {
            "label": "uint8",
            "numberOfBytes": "1"
          }
        }
      }
    },
    "be23b959dad5a161adb147b31927c4240043a9528ba607233f5aa32be50d4dbd": {
      "address": "0x5d12c5E5cD4B3b2fCeee3F320729538C39f5d8c8",
      "txHash": "0x9ddfd08f2488d8ec361af2a1db0cc08f0e11096560cb656efaa5273192a57cee",
      "layout": {
        "solcVersion": "0.8.13",
        "storage": [
          {
            "label": "_initialized",
            "offset": 0,
            "slot": "0",
            "type": "t_uint8",
            "contract": "Initializable",
            "src": "@openzeppelin/contracts-upgradeable/proxy/utils/Initializable.sol:62",
            "retypedFrom": "bool"
          },
          {
            "label": "_initializing",
            "offset": 1,
            "slot": "0",
            "type": "t_bool",
            "contract": "Initializable",
            "src": "@openzeppelin/contracts-upgradeable/proxy/utils/Initializable.sol:67"
          },
          {
            "label": "pairFactory",
            "offset": 2,
            "slot": "0",
            "type": "t_contract(IPairFactory)2136",
            "contract": "PairAPI",
            "src": "contracts/APIHelper/PairAPI.sol:85"
          },
          {
            "label": "voter",
            "offset": 0,
            "slot": "1",
            "type": "t_contract(IVoter)2249",
            "contract": "PairAPI",
            "src": "contracts/APIHelper/PairAPI.sol:86"
          },
          {
            "label": "underlyingToken",
            "offset": 0,
            "slot": "2",
            "type": "t_address",
            "contract": "PairAPI",
            "src": "contracts/APIHelper/PairAPI.sol:88"
          },
          {
            "label": "owner",
            "offset": 0,
            "slot": "3",
            "type": "t_address",
            "contract": "PairAPI",
            "src": "contracts/APIHelper/PairAPI.sol:90"
          }
        ],
        "types": {
          "t_address": {
            "label": "address",
            "numberOfBytes": "20"
          },
          "t_bool": {
            "label": "bool",
            "numberOfBytes": "1"
          },
          "t_contract(IPairFactory)2136": {
            "label": "contract IPairFactory",
            "numberOfBytes": "20"
          },
          "t_contract(IVoter)2249": {
            "label": "contract IVoter",
            "numberOfBytes": "20"
          },
          "t_uint8": {
            "label": "uint8",
            "numberOfBytes": "1"
          }
        }
      }
    },
    "520eab392db49607a40ca3f77d526390f6c4283a4174212fab0b487079360f5b": {
      "address": "0x50E96a75DE6ae80A9D6C5313AEd908aFd369baee",
      "txHash": "0xfa32290cee0a3503333860fd8471cb93de85c433ac92319be10bafc3ac4d7fd4",
      "layout": {
        "solcVersion": "0.8.13",
        "storage": [
          {
            "label": "_initialized",
            "offset": 0,
            "slot": "0",
            "type": "t_uint8",
            "contract": "Initializable",
            "src": "@openzeppelin/contracts-upgradeable/proxy/utils/Initializable.sol:62",
            "retypedFrom": "bool"
          },
          {
            "label": "_initializing",
            "offset": 1,
            "slot": "0",
            "type": "t_bool",
            "contract": "Initializable",
            "src": "@openzeppelin/contracts-upgradeable/proxy/utils/Initializable.sol:67"
          },
          {
            "label": "pairFactory",
            "offset": 2,
            "slot": "0",
            "type": "t_contract(IPairFactory)10703",
            "contract": "PairAPI",
            "src": "contracts/APIHelper/PairAPI.sol:85"
          },
          {
            "label": "voter",
            "offset": 0,
            "slot": "1",
            "type": "t_contract(IVoter)10935",
            "contract": "PairAPI",
            "src": "contracts/APIHelper/PairAPI.sol:86"
          },
          {
            "label": "underlyingToken",
            "offset": 0,
            "slot": "2",
            "type": "t_address",
            "contract": "PairAPI",
            "src": "contracts/APIHelper/PairAPI.sol:88"
          },
          {
            "label": "owner",
            "offset": 0,
            "slot": "3",
            "type": "t_address",
            "contract": "PairAPI",
            "src": "contracts/APIHelper/PairAPI.sol:90"
          }
        ],
        "types": {
          "t_address": {
            "label": "address",
            "numberOfBytes": "20"
          },
          "t_bool": {
            "label": "bool",
            "numberOfBytes": "1"
          },
          "t_contract(IPairFactory)10703": {
            "label": "contract IPairFactory",
            "numberOfBytes": "20"
          },
          "t_contract(IVoter)10935": {
            "label": "contract IVoter",
            "numberOfBytes": "20"
          },
          "t_uint8": {
            "label": "uint8",
            "numberOfBytes": "1"
          }
        }
      }
    },
    "9f54bc1f9637711d2a032b7fb6f5bf82cab272ed7a62c66a6dd1307f20bc96ee": {
      "address": "0xE355FfaE5d1adBa3BD730ecCEc37B48E221155e2",
      "txHash": "0x0350e9003e10b68023098cf8b104da89f592da0b4b8d3d860ded5494b68a7851",
      "layout": {
        "solcVersion": "0.8.13",
        "storage": [
          {
            "label": "_initialized",
            "offset": 0,
            "slot": "0",
            "type": "t_uint8",
            "contract": "Initializable",
            "src": "@openzeppelin/contracts-upgradeable/proxy/utils/Initializable.sol:62",
            "retypedFrom": "bool"
          },
          {
            "label": "_initializing",
            "offset": 1,
            "slot": "0",
            "type": "t_bool",
            "contract": "Initializable",
            "src": "@openzeppelin/contracts-upgradeable/proxy/utils/Initializable.sol:67"
          },
          {
            "label": "pairFactory",
            "offset": 2,
            "slot": "0",
            "type": "t_contract(IPairFactory)10703",
            "contract": "RewardAPI",
            "src": "contracts/APIHelper/RewardAPI.sol:25"
          },
          {
            "label": "voter",
            "offset": 0,
            "slot": "1",
            "type": "t_contract(IVoter)10935",
            "contract": "RewardAPI",
            "src": "contracts/APIHelper/RewardAPI.sol:26"
          },
          {
            "label": "underlyingToken",
            "offset": 0,
            "slot": "2",
            "type": "t_address",
            "contract": "RewardAPI",
            "src": "contracts/APIHelper/RewardAPI.sol:27"
          },
          {
            "label": "owner",
            "offset": 0,
            "slot": "3",
            "type": "t_address",
            "contract": "RewardAPI",
            "src": "contracts/APIHelper/RewardAPI.sol:28"
          }
        ],
        "types": {
          "t_address": {
            "label": "address",
            "numberOfBytes": "20"
          },
          "t_bool": {
            "label": "bool",
            "numberOfBytes": "1"
          },
          "t_contract(IPairFactory)10703": {
            "label": "contract IPairFactory",
            "numberOfBytes": "20"
          },
          "t_contract(IVoter)10935": {
            "label": "contract IVoter",
            "numberOfBytes": "20"
          },
          "t_uint8": {
            "label": "uint8",
            "numberOfBytes": "1"
          }
        }
      }
    },
    "3097e5a8d3be2dcde799f158b6a40d11e5d231cb1d76620feb40b9f7815c4c3b": {
      "address": "0xF70Cf6ab99aA8dad10c7f8742d9F125cCfDDF8d0",
      "txHash": "0x7d0044b44df8b5d2700c1469523f2835af4c3b63581b16cf980367159326fe74",
      "layout": {
        "solcVersion": "0.8.13",
        "storage": [
          {
            "label": "_initialized",
            "offset": 0,
            "slot": "0",
            "type": "t_uint8",
            "contract": "Initializable",
            "src": "@openzeppelin/contracts-upgradeable/proxy/utils/Initializable.sol:62",
            "retypedFrom": "bool"
          },
          {
            "label": "_initializing",
            "offset": 1,
            "slot": "0",
            "type": "t_bool",
            "contract": "Initializable",
            "src": "@openzeppelin/contracts-upgradeable/proxy/utils/Initializable.sol:67"
          },
          {
            "label": "pairFactory",
            "offset": 2,
            "slot": "0",
            "type": "t_contract(IPairFactory)4000",
            "contract": "PairAPI",
            "src": "contracts/APIHelper/PairAPI.sol:85"
          },
          {
            "label": "voter",
            "offset": 0,
            "slot": "1",
            "type": "t_contract(IVoter)4134",
            "contract": "PairAPI",
            "src": "contracts/APIHelper/PairAPI.sol:86"
          },
          {
            "label": "underlyingToken",
            "offset": 0,
            "slot": "2",
            "type": "t_address",
            "contract": "PairAPI",
            "src": "contracts/APIHelper/PairAPI.sol:88"
          },
          {
            "label": "owner",
            "offset": 0,
            "slot": "3",
            "type": "t_address",
            "contract": "PairAPI",
            "src": "contracts/APIHelper/PairAPI.sol:90"
          }
        ],
        "types": {
          "t_address": {
            "label": "address",
            "numberOfBytes": "20"
          },
          "t_bool": {
            "label": "bool",
            "numberOfBytes": "1"
          },
          "t_contract(IPairFactory)4000": {
            "label": "contract IPairFactory",
            "numberOfBytes": "20"
          },
          "t_contract(IVoter)4134": {
            "label": "contract IVoter",
            "numberOfBytes": "20"
          },
          "t_uint8": {
            "label": "uint8",
            "numberOfBytes": "1"
          }
        }
      }
    },
    "316b12d7fc59328f605b2544e5dfe3285f131805b82c0c202ad9fd76e8327117": {
      "address": "0x448A53f5256Ad5416Cd6f6ed50F17445664e9642",
      "txHash": "0x771df96926a121fe19073f909d8184207b91f2351b98e14c4e0c2d0367ca9659",
      "layout": {
        "solcVersion": "0.8.13",
        "storage": [
          {
            "label": "_initialized",
            "offset": 0,
            "slot": "0",
            "type": "t_uint8",
            "contract": "Initializable",
            "src": "@openzeppelin/contracts-upgradeable/proxy/utils/Initializable.sol:62",
            "retypedFrom": "bool"
          },
          {
            "label": "_initializing",
            "offset": 1,
            "slot": "0",
            "type": "t_bool",
            "contract": "Initializable",
            "src": "@openzeppelin/contracts-upgradeable/proxy/utils/Initializable.sol:67"
          },
          {
            "label": "pairFactory",
            "offset": 2,
            "slot": "0",
            "type": "t_contract(IPairFactory)4000",
            "contract": "RewardAPI",
            "src": "contracts/APIHelper/RewardAPI.sol:25"
          },
          {
            "label": "voter",
            "offset": 0,
            "slot": "1",
            "type": "t_contract(IVoter)4134",
            "contract": "RewardAPI",
            "src": "contracts/APIHelper/RewardAPI.sol:26"
          },
          {
            "label": "underlyingToken",
            "offset": 0,
            "slot": "2",
            "type": "t_address",
            "contract": "RewardAPI",
            "src": "contracts/APIHelper/RewardAPI.sol:27"
          },
          {
            "label": "owner",
            "offset": 0,
            "slot": "3",
            "type": "t_address",
            "contract": "RewardAPI",
            "src": "contracts/APIHelper/RewardAPI.sol:28"
          }
        ],
        "types": {
          "t_address": {
            "label": "address",
            "numberOfBytes": "20"
          },
          "t_bool": {
            "label": "bool",
            "numberOfBytes": "1"
          },
          "t_contract(IPairFactory)4000": {
            "label": "contract IPairFactory",
            "numberOfBytes": "20"
          },
          "t_contract(IVoter)4134": {
            "label": "contract IVoter",
            "numberOfBytes": "20"
          },
          "t_uint8": {
            "label": "uint8",
            "numberOfBytes": "1"
          }
        }
      }
    },
    "e39671f97b69d3193d6b480796af276bd0b6c10211a0211264c5aea98b50abdb": {
      "address": "0xb3ADE3aC69FEe3cf2b49ad91Cdc8716735cF2E7b",
      "txHash": "0x053ec7ab3ee63ab8066861c40890e87275a6e1dbc815e37fba871b07c1f2cf11",
      "layout": {
        "solcVersion": "0.8.13",
        "storage": [
          {
            "label": "_initialized",
            "offset": 0,
            "slot": "0",
            "type": "t_uint8",
            "contract": "Initializable",
            "src": "@openzeppelin/contracts-upgradeable/proxy/utils/Initializable.sol:62",
            "retypedFrom": "bool"
          },
          {
            "label": "_initializing",
            "offset": 1,
            "slot": "0",
            "type": "t_bool",
            "contract": "Initializable",
            "src": "@openzeppelin/contracts-upgradeable/proxy/utils/Initializable.sol:67"
          },
          {
            "label": "voter",
            "offset": 2,
            "slot": "0",
            "type": "t_contract(IVoter)4134",
            "contract": "veNFTAPI",
            "src": "contracts/APIHelper/veNFTAPI.sol:109"
          },
          {
            "label": "underlyingToken",
            "offset": 0,
            "slot": "1",
            "type": "t_address",
            "contract": "veNFTAPI",
            "src": "contracts/APIHelper/veNFTAPI.sol:110"
          },
          {
            "label": "ve",
            "offset": 0,
            "slot": "2",
            "type": "t_contract(IVotingEscrow)4317",
            "contract": "veNFTAPI",
            "src": "contracts/APIHelper/veNFTAPI.sol:113"
          },
          {
            "label": "rewardDisitributor",
            "offset": 0,
            "slot": "3",
            "type": "t_contract(IRewardsDistributor)4021",
            "contract": "veNFTAPI",
            "src": "contracts/APIHelper/veNFTAPI.sol:114"
          },
          {
            "label": "pairAPI",
            "offset": 0,
            "slot": "4",
            "type": "t_address",
            "contract": "veNFTAPI",
            "src": "contracts/APIHelper/veNFTAPI.sol:116"
          },
          {
            "label": "pairFactory",
            "offset": 0,
            "slot": "5",
            "type": "t_contract(IPairFactory)4000",
            "contract": "veNFTAPI",
            "src": "contracts/APIHelper/veNFTAPI.sol:117"
          },
          {
            "label": "owner",
            "offset": 0,
            "slot": "6",
            "type": "t_address",
            "contract": "veNFTAPI",
            "src": "contracts/APIHelper/veNFTAPI.sol:120"
          }
        ],
        "types": {
          "t_address": {
            "label": "address",
            "numberOfBytes": "20"
          },
          "t_bool": {
            "label": "bool",
            "numberOfBytes": "1"
          },
          "t_contract(IPairFactory)4000": {
            "label": "contract IPairFactory",
            "numberOfBytes": "20"
          },
          "t_contract(IRewardsDistributor)4021": {
            "label": "contract IRewardsDistributor",
            "numberOfBytes": "20"
          },
          "t_contract(IVoter)4134": {
            "label": "contract IVoter",
            "numberOfBytes": "20"
          },
          "t_contract(IVotingEscrow)4317": {
            "label": "contract IVotingEscrow",
            "numberOfBytes": "20"
          },
          "t_uint8": {
            "label": "uint8",
            "numberOfBytes": "1"
          }
        }
      }
    }
  }
}
